personallize/.gitattributes
personallize/__init__.py
personallize/__main__.py
personallize/connection.py
personallize/entity_factory.py
personallize/project_structure.py
personallize/py.typed
personallize/simple_log.py
personallize/webdriver_factory.py
personallize/complex_log/__init__.py
personallize/complex_log/config.py
personallize/complex_log/formatters.py
personallize/complex_log/manager.py
personallize-1.2.0.dist-info/METADATA
personallize-1.2.0.dist-info/WHEEL
personallize-1.2.0.dist-info/entry_points.txt
personallize-1.2.0.dist-info/licenses/LICENSE
personallize-1.2.0.dist-info/RECORD
