Metadata-Version: 2.4
Name: personallize
Version: 1.2.0
Summary: Biblioteca Python com ferramentas essenciais para desenvolvimento de RPA e ML, oferecendo recursos para conexão com bancos de dados, logging, ORM, geração de estruturas de projeto e interface CLI.
Project-URL: Homepage, https://github.com/MiguelTenorio42/personallize
Project-URL: Bug Reports, https://github.com/MiguelTenorio42/personallize/issues
Project-URL: Source, https://github.com/MiguelTenorio42/personallize
Project-URL: Documentation, https://github.com/MiguelTenorio42/personallize#readme
Author-email: Miguel Tenório <deepydev42@gmail.com>
Maintainer-email: Miguel Tenório <deepydev42@gmail.com>
License: MIT
License-File: LICENSE
Keywords: cli,database,logging,ml,orm,performance,project-generator,rpa,scaffolding,selenium,sqlalchemy,webdriver
Classifier: Development Status :: 4 - Beta
Classifier: Environment :: Console
Classifier: Intended Audience :: Developers
Classifier: License :: OSI Approved :: MIT License
Classifier: Operating System :: OS Independent
Classifier: Programming Language :: Python :: 3
Classifier: Programming Language :: Python :: 3.11
Classifier: Programming Language :: Python :: 3.12
Classifier: Programming Language :: Python :: 3.13
Classifier: Topic :: Database
Classifier: Topic :: Software Development :: Code Generators
Classifier: Topic :: Software Development :: Libraries :: Python Modules
Classifier: Topic :: System :: Logging
Requires-Python: >=3.11
Requires-Dist: colorama>=0.4.4
Requires-Dist: psutil>=5.8.0
Requires-Dist: psycopg2-binary>=2.9.0
Requires-Dist: pymysql>=1.0.0
Requires-Dist: pyodbc>=4.0.0
Requires-Dist: rich>=12.0.0
Requires-Dist: selenium>=4.0.0
Requires-Dist: sqlalchemy>=2.0.0
Requires-Dist: tzdata>=2021.1
Requires-Dist: webdriver-manager>=3.8.0
Provides-Extra: dev
Requires-Dist: blue>=0.9.0; extra == 'dev'
Requires-Dist: mypy>=0.800; extra == 'dev'
Requires-Dist: pytest>=7.0.0; extra == 'dev'
Requires-Dist: ruff>=0.1.0; extra == 'dev'
